taggerdb/__init__.py
taggerdb/__main__.py
taggerdb/taggerdb.py
taggerdb-0.1.2.dist-info/LICENSE
taggerdb-0.1.2.dist-info/METADATA
taggerdb-0.1.2.dist-info/WHEEL
taggerdb-0.1.2.dist-info/entry_points.txt
taggerdb-0.1.2.dist-info/top_level.txt
taggerdb-0.1.2.dist-info/RECORD
