Metadata-Version: 2.1
Name: taggerdb
Version: 0.1.2
Summary: A user-friendly tool designed for managing and tagging files
Home-page: https://github.com/angelojrdev/taggerdb
Author: Angelo Oliveira Jr.
Author-email: 43245439+angelojrdev@users.noreply.github.com
Classifier: Programming Language :: Python :: 3
Classifier: License :: OSI Approved :: GNU General Public License v3 (GPLv3)
Classifier: Operating System :: OS Independent
Requires-Python: >=3.6
License-File: LICENSE
